exec_wrappers/__init__.py
exec_wrappers/create_wrappers.py
exec_wrappers/templates/conda/run-in
exec_wrappers/templates/conda/run-in.bat
exec_wrappers/templates/schroot/run-in
exec_wrappers/templates/virtualenv/run-in
exec_wrappers/templates/virtualenv/run-in.bat
exec_wrappers-1.1.4.dist-info/LICENSE
exec_wrappers-1.1.4.dist-info/METADATA
exec_wrappers-1.1.4.dist-info/WHEEL
exec_wrappers-1.1.4.dist-info/entry_points.txt
exec_wrappers-1.1.4.dist-info/top_level.txt
exec_wrappers-1.1.4.dist-info/RECORD
