Metadata-Version: 2.1
Name: exec-wrappers
Version: 1.1.4
Summary: wrappers for running commands that need some initial setup
Home-page: https://github.com/gqmelo/exec-wrappers
Author: Guilherme Quentel Melo
Author-email: gqmelo@gmail.com
License: MIT
Platform: UNKNOWN
Classifier: Development Status :: 5 - Production/Stable
Classifier: Intended Audience :: Developers
Classifier: Operating System :: OS Independent
Classifier: Programming Language :: Python :: 2
Classifier: Programming Language :: Python :: 2.7
Classifier: Programming Language :: Python :: 3
Classifier: Programming Language :: Python :: 3.4
Classifier: Programming Language :: Python :: 3.5
Classifier: Programming Language :: Python :: 3.6
Classifier: Programming Language :: Python :: 3.7
